Metadata-Version: 1.1
Name: pyfootball
Version: 1.0.1
Summary: A client library for the football-data.org REST API
Home-page: https://github.com/xozzo/pyfootball
Author: Timothy Ng
Author-email: hello@timothyng.xyz
License: MIT
Keywords: api wrapper client library football data
Platform: UNKNOWN
Classifier: Development Status :: 5 - Production/Stable
Classifier: Intended Audience :: Developers
Classifier: Topic :: Software Development :: Libraries
Classifier: License :: OSI Approved :: MIT License
Classifier: Programming Language :: Python :: 3.5
